mlnames/__init__.py
mlnames/corpus
mlnames/exclude_words
mlnames-0.1.3.dist-info/METADATA
mlnames-0.1.3.dist-info/WHEEL
mlnames-0.1.3.dist-info/top_level.txt
mlnames-0.1.3.dist-info/RECORD
